async_unshortenit/__init__.py
async_unshortenit/__version__.py
async_unshortenit/async_unshortenit.py
async_unshortenit/exceptions.py
async_unshortenit/module.py
async_unshortenit/modules/__init__.py
async_unshortenit/modules/adfly.py
async_unshortenit/modules/adfocus.py
async_unshortenit/modules/linkbucks.py
async_unshortenit/modules/meta_refresh.py
async_unshortenit/modules/redirect.py
async_unshortenit/modules/shortest.py
async_unshortenit-0.1.0.dist-info/METADATA
async_unshortenit-0.1.0.dist-info/WHEEL
async_unshortenit-0.1.0.dist-info/top_level.txt
async_unshortenit-0.1.0.dist-info/zip-safe
async_unshortenit-0.1.0.dist-info/RECORD
